{
  "resourceType": "Bundle",
  "id": "eve-lastTestColonoscopy_yes_eve-colonoscopyFindingCRC_yes_act-oncologyReferral",
  "type": "collection",
  "entry": [
    {
      "resource": {
        "resourceType": "Patient",
        "id": "d25bf765-396b-48f1-a5ba-ee2222376642",
        "name": [
          {
            "given": [
              "Joanne"
            ],
            "family": "Smith"
          }
        ],
        "gender": "other",
        "birthDate": "1971-01-01",
        "extension": [
          {
            "url": "http://hl7.org/fhir/us/core/StructureDefinition/us-core-birthsex",
            "valueCode": "F"
          }
        ]
      }
    },
    {
      "resource": {
        "resourceType": "DiagnosticReport",
        "id": "colonoscopy-report-crc",
        "subject": {
          "reference": "Patient/d25bf765-396b-48f1-a5ba-ee2222376642"
        },
        "status": "final",
        "code": {
          "coding": [
            {
              "system": "http://loinc.org",
              "code": "18746-8",
              "display": "Colonoscopy study"
            }
          ]
        },
        "conclusionCode": [
          {
            "coding": [
              {
                "system": "http://snomed.info/sct",
                "code": "363406005",
                "display": "Malignant neoplasm of colon (disorder)"
              }
            ]
          }
        ],
        "effectiveDateTime": "2024-10-01T00:00:00.000Z"
      }
    }
  ]
}