{
  "resourceType": "Bundle",
  "id": "IsScreeningEligible_true",
  "type": "collection",
  "entry": [
    {
      "resource": {
        "resourceType": "Patient",
        "id": "2a645d06-ab59-4b03-aa5e-c0c7c4171077",
        "name": [
          {
            "given": [
              "Joanne"
            ],
            "family": "Smith"
          }
        ],
        "gender": "other",
        "birthDate": "1971-01-01",
        "extension": [
          {
            "url": "http://hl7.org/fhir/us/core/StructureDefinition/us-core-birthsex",
            "valueCode": "F"
          }
        ]
      }
    }
  ]
}