{
  "resourceType": "Bundle",
  "id": "FollowUp_eve-lastTestColonoscopy_no_eve-lastTestStool_yes_eve-inconclusiveStoolTest_no_eve-abnormalStoolTest_no_end-1",
  "type": "collection",
  "entry": [
    {
      "fullUrl": "http://cancerscreeningcds.github.io/crcsm-cds/CarePlan/145",
      "resource": {
        "resourceType": "CarePlan",
        "id": "145",
        "subject": {
          "reference": "Patient/e6e706b8-d499-4d24-9a38-d1c6143df63e",
          "display": "Joanne Smith"
        },
        "instantiatesCanonical": [
          "http://cancerscreeningcds.github.io/crcsm-cds/PlanDefinition/flow-FollowUp"
        ],
        "intent": "proposal",
        "status": "draft",
        "created": "2024-12-10T00:00:00.0Z",
        "activity": [
          {
            "reference": {
              "reference": "RequestGroup/146"
            }
          }
        ]
      }
    },
    {
      "fullUrl": "http://cancerscreeningcds.github.io/crcsm-cds/RequestGroup/146",
      "resource": {
        "resourceType": "RequestGroup",
        "id": "146",
        "subject": {
          "reference": "Patient/e6e706b8-d499-4d24-9a38-d1c6143df63e",
          "display": "Joanne Smith"
        },
        "instantiatesCanonical": [
          "http://cancerscreeningcds.github.io/crcsm-cds/PlanDefinition/flow-FollowUp"
        ],
        "intent": "proposal",
        "status": "draft",
        "action": []
      }
    }
  ]
}